arithmetic_eval/__init__.py
arithmetic_eval/constants.py
arithmetic_eval/exceptions.py
arithmetic_eval/tests.py
arithmetic_eval/utils.py
arithmeval-0.3.4.dist-info/licenses/LICENSE
arithmeval-0.3.4.dist-info/METADATA
arithmeval-0.3.4.dist-info/WHEEL
arithmeval-0.3.4.dist-info/top_level.txt
arithmeval-0.3.4.dist-info/RECORD
