Metadata-Version: 2.4
Name: arithmeval
Version: 0.3.4
Summary: A package that lets you safely evaluate arithmetic expressions.
Home-page: https://github.com/enesklcarslan/arithmeval/
Author: Enes Kilicarslan
Author-email: enesklcarslan@gmail.com
License: BSD-3-Clause
Classifier: Environment :: Web Environment
Classifier: Intended Audience :: Developers
Classifier: License :: OSI Approved :: BSD License
Classifier: Operating System :: OS Independent
Classifier: Programming Language :: Python :: 3.9
Requires-Python: >=3.8
License-File: LICENSE
Dynamic: license-file
